cloe_snowflake_rbac/__init__.py
cloe_snowflake_rbac/functional_roles/__init__.py
cloe_snowflake_rbac/functional_roles/database_grant.py
cloe_snowflake_rbac/functional_roles/functional_role.py
cloe_snowflake_rbac/functional_roles/schema_grant.py
cloe_snowflake_rbac/functional_roles/warehouse_grant.py
cloe_snowflake_rbac/main.py
cloe_snowflake_rbac/py.typed
cloe_snowflake_rbac/technical_roles/__init__.py
cloe_snowflake_rbac/technical_roles/technical_roles.py
cloe_snowflake_rbac/templates/__init__.py
cloe_snowflake_rbac/templates/functional_roles/__init__.py
cloe_snowflake_rbac/templates/functional_roles/set_database_privileges.sql.j2
cloe_snowflake_rbac/templates/functional_roles/set_schema_privileges.sql.j2
cloe_snowflake_rbac/templates/functional_roles/set_warehouse_privileges.sql.j2
cloe_snowflake_rbac/templates/technical_roles/__init__.py
cloe_snowflake_rbac/templates/technical_roles/role_db_owner.sql.j2
cloe_snowflake_rbac/templates/technical_roles/role_execute.sql.j2
cloe_snowflake_rbac/templates/technical_roles/role_ownership.sql.j2
cloe_snowflake_rbac/templates/technical_roles/role_read.sql.j2
cloe_snowflake_rbac/templates/technical_roles/role_write.sql.j2
cloe_snowflake_rbac/utils/__init__.py
cloe_snowflake_rbac/utils/compare_databases.py
cloe_snowflake_rbac/utils/compare_functional_roles.py
cloe_snowflake_rbac/utils/read_text_from_disk.py
cloe_snowflake_rbac/utils/read_yaml_from_disk.py
cloe_snowflake_rbac/utils/recreate_file_structure.py
cloe_snowflake_rbac/utils/role_deployment.py
cloe_snowflake_rbac/utils/template_env.py
cloe_snowflake_rbac-2.0.7.dist-info/licenses/LICENSE
cloe_snowflake_rbac-2.0.7.dist-info/WHEEL
cloe_snowflake_rbac-2.0.7.dist-info/entry_points.txt
cloe_snowflake_rbac-2.0.7.dist-info/METADATA
cloe_snowflake_rbac-2.0.7.dist-info/RECORD
