Metadata-Version: 2.4
Name: cloe-snowflake-rbac
Version: 2.0.7
Summary: Package is a full metadata driven role based access control framework.
Keywords: 
Author: initions
Author-email: initions <ICSMC_EXT_PYPIORG@accenture.com>
License-Expression: MIT
License-File: LICENSE
Classifier: Development Status :: 5 - Production/Stable
Classifier: Environment :: Console
Classifier: Intended Audience :: Developers
Classifier: Operating System :: OS Independent
Classifier: Programming Language :: Python :: 3
Classifier: Topic :: Database
Requires-Dist: jinja2~=3.1.2
Requires-Dist: cloe-metadata~=2.2.2
Requires-Dist: cloe-util-snowflake-connector~=1.0.5
Requires-Dist: cloe-util-git-client~=2.0.0
Requires-Dist: typer[all]~=0.16.0
Requires-Dist: click~=8.2
Requires-Python: >=3.11, <3.12
